satzreduktion/__init__.py
satzreduktion/cli.py
satzreduktion/satzreduktion.py
satzreduktion-1.0.0.dist-info/AUTHORS.rst
satzreduktion-1.0.0.dist-info/METADATA
satzreduktion-1.0.0.dist-info/WHEEL
satzreduktion-1.0.0.dist-info/entry_points.txt
satzreduktion-1.0.0.dist-info/top_level.txt
satzreduktion-1.0.0.dist-info/RECORD
