Metadata-Version: 2.1
Name: satzreduktion
Version: 1.0.0
Summary: Satzreduktion mithilfe von NER Tools
Home-page: https://git.informatik.uni-leipzig.de/nw20hewo/satz-reduktion
Author: Gruppe-4-2
Author-email: nw20hewo@studserv.uni-leipzig.de
License: UNKNOWN
Keywords: satzreduktion
Platform: UNKNOWN
Classifier: Development Status :: 2 - Pre-Alpha
Classifier: Intended Audience :: Developers
Classifier: Natural Language :: English
Classifier: Programming Language :: Python :: 2
Classifier: Programming Language :: Python :: 2.7
Classifier: Programming Language :: Python :: 3
Classifier: Programming Language :: Python :: 3.4
Classifier: Programming Language :: Python :: 3.5
Classifier: Programming Language :: Python :: 3.6
Classifier: Programming Language :: Python :: 3.7
Requires-Dist: Click (>=6.0)
Requires-Dist: flair
